LICENSE
MANIFEST.in
README.md
setup.py
examples/forceatlas2-layout.ipynb
examples/geometric_graph.png
examples/grid_graph.png
fa2/__init__.py
fa2/fa2util.c
fa2/fa2util.pxd
fa2/fa2util.py
fa2/forceatlas2.py
forceatlas2py.egg-info/PKG-INFO
forceatlas2py.egg-info/SOURCES.txt
forceatlas2py.egg-info/dependency_links.txt
forceatlas2py.egg-info/not-zip-safe
forceatlas2py.egg-info/requires.txt
forceatlas2py.egg-info/top_level.txt