Metadata-Version: 2.1
Name: forceatlas2py
Version: 0.1.1
Summary: The fastest ForceAtlas2 algorithm for Python (and NetworkX)
Home-page: https://gitlab.com/deep-seer/forceatlas2py
Author: Oliver Wilkinson
Author-email: oliver.wilkinson@unai.com
License: UNKNOWN
Download-URL: https://gitlab.com/deep-seer/forceatlas2py/-/archive/master/forceatlas2py-master.tar.gz
Keywords: forceatlas2,networkx,force-directed-graph,force-layout,graph
Platform: UNKNOWN
Classifier: Development Status :: 5 - Production/Stable
Classifier: Intended Audience :: Science/Research
Classifier: Topic :: Scientific/Engineering :: Mathematics
Classifier: License :: OSI Approved :: GNU General Public License v3 (GPLv3)
Classifier: Programming Language :: Python :: 2
Classifier: Programming Language :: Python :: 3
Requires-Python: >=3.7
Provides-Extra: networkx
Provides-Extra: igraph
